botor/__about__.py
botor/__init__.py
botor/decorators.py
botor/exceptions.py
botor/aws/__init__.py
botor/aws/autoscaling.py
botor/aws/ec2.py
botor/aws/iam.py
botor/aws/sqs.py
botor/aws/sts.py
botor-0.0.1dev4.dist-info/DESCRIPTION.rst
botor-0.0.1dev4.dist-info/METADATA
botor-0.0.1dev4.dist-info/metadata.json
botor-0.0.1dev4.dist-info/RECORD
botor-0.0.1dev4.dist-info/top_level.txt
botor-0.0.1dev4.dist-info/WHEEL
