Metadata-Version: 2.0
Name: botor
Version: 0.0.1dev4
Summary: A thin wrapper around boto3
Home-page: https://github.com/monkeysecurity/botor
Author: Patrick Kelley
Author-email: patrick@netflix.com
License: UNKNOWN
Platform: UNKNOWN
Requires-Dist: boto3 (>=1.2.3)
Requires-Dist: boto (>=2.39.0)
Requires-Dist: joblib (>=0.9.4)
Provides-Extra: docs
Provides-Extra: tests
Provides-Extra: dev
